ascend_npu_utils/__init__.py
ascend_npu_utils/utils.py
ascend_npu_utils-0.1.1.dist-info/METADATA
ascend_npu_utils-0.1.1.dist-info/WHEEL
ascend_npu_utils-0.1.1.dist-info/top_level.txt
ascend_npu_utils-0.1.1.dist-info/RECORD
