Metadata-Version: 2.1
Name: ascend-npu-utils
Version: 0.1.1
Summary: A utility library for interacting with Ascend NPUs via the npu-smi command options, to directly get information from the terminal commands parsed into python
Author: Harsh
Classifier: Programming Language :: Python :: 3
Classifier: License :: OSI Approved :: MIT License
Classifier: Operating System :: OS Independent
Requires-Python: >=3.6
Requires-Dist: psutil
